{
  "name": "587296_main_page_51_table_1",
  "rows": [
    [
      {
        "colspan": 1,
        "content": "Quick-Load\u00ae Purple 1 kb DNA Ladder"
      },
      {
        "colspan": 1,
        "content": "New England Biolabs, B7025"
      }
    ],
    [
      {
        "colspan": 2,
        "content": "Reporter-gene Assays"
      }
    ],
    [
      {
        "colspan": 1,
        "content": "Dual-Luciferase\u00ae Reporter Assay System"
      },
      {
        "colspan": 1,
        "content": "Promega, E1910"
      }
    ],
    [
      {
        "colspan": 1,
        "content": "ONE-Glo\u2122 Luciferase Assay System"
      },
      {
        "colspan": 1,
        "content": "Promega, E6110"
      }
    ],
    [
      {
        "colspan": 2,
        "content": "Machines & Software"
      }
    ],
    [
      {
        "colspan": 1,
        "content": "CellDrop FL"
      },
      {
        "colspan": 1,
        "content": "DeNovix"
      }
    ],
    [
      {
        "colspan": 1,
        "content": "Nanodrop 2000c Spectrophotometer"
      },
      {
        "colspan": 1,
        "content": "peqlab"
      }
    ],
    [
      {
        "colspan": 1,
        "content": "Odyssey CLx Fluorescence Imager"
      },
      {
        "colspan": 1,
        "content": "LI-COR"
      }
    ],
    [
      {
        "colspan": 1,
        "content": "Biometra Tadvanced"
      },
      {
        "colspan": 1,
        "content": "Analytik Jena"
      }
    ],
    [
      {
        "colspan": 1,
        "content": "CFX384 Touch Real-Time PCR Detection System"
      },
      {
        "colspan": 1,
        "content": "Bio-Rad"
      }
    ],
    [
      {
        "colspan": 1,
        "content": "CFX Opus 96 Real-Time PCR System"
      },
      {
        "colspan": 1,
        "content": "Bio-Rad"
      }
    ],
    [
      {
        "colspan": 1,
        "content": "PowerPac 300"
      },
      {
        "colspan": 1,
        "content": "Bio-Rad"
      }
    ],
    [
      {
        "colspan": 1,
        "content": "Omega Fluor Plus"
      },
      {
        "colspan": 1,
        "content": "Aplegen"
      }
    ],
    [
      {
        "colspan": 1,
        "content": "Chemidoc Imaging System"
      },
      {
        "colspan": 1,
        "content": "Bio-Rad"
      }
    ],
    [
      {
        "colspan": 1,
        "content": "Excelsior Tissue Processor"
      },
      {
        "colspan": 1,
        "content": "Histocom"
      }
    ],
    [
      {
        "colspan": 1,
        "content": "Histostar embedding station"
      },
      {
        "colspan": 1,
        "content": "Histocom"
      }
    ],
    [
      {
        "colspan": 1,
        "content": "RM2255 Fully Automated Rotary Microtome"
      },
      {
        "colspan": 1,
        "content": "Leica"
      }
    ],
    [
      {
        "colspan": 1,
        "content": "Axio Imager.Z2"
      },
      {
        "colspan": 1,
        "content": "Zeiss"
      }
    ],
    [
      {
        "colspan": 1,
        "content": "Axivert 135 TV"
      },
      {
        "colspan": 1,
        "content": "Zeiss"
      }
    ],
    [
      {
        "colspan": 1,
        "content": "LSM 510 Confocal Microscope"
      },
      {
        "colspan": 1,
        "content": "Zeiss"
      }
    ],
    [
      {
        "colspan": 1,
        "content": "BD FACSCalibur\u2122 Flow Cytometer"
      },
      {
        "colspan": 1,
        "content": "BD Biosciences"
      }
    ],
    [
      {
        "colspan": 1,
        "content": "BD CellQuest\u2122 Pro Software"
      },
      {
        "colspan": 1,
        "content": "BD Biosciences"
      }
    ],
    [
      {
        "colspan": 1,
        "content": "FlowJo v10.4"
      },
      {
        "colspan": 1,
        "content": "BD Biosciences"
      }
    ],
    [
      {
        "colspan": 1,
        "content": "Photoshop CS2\u2122"
      },
      {
        "colspan": 1,
        "content": "Adobe"
      }
    ],
    [
      {
        "colspan": 1,
        "content": "Maestro CFX1.1 Software"
      },
      {
        "colspan": 1,
        "content": "Bio-Rad"
      }
    ],
    [
      {
        "colspan": 1,
        "content": "Excel 2013"
      },
      {
        "colspan": 1,
        "content": "Microsoft"
      }
    ],
    [
      {
        "colspan": 1,
        "content": "Graph Pad 5"
      },
      {
        "colspan": 1,
        "content": "Prism"
      }
    ],
    [
      {
        "colspan": 2,
        "content": "Other"
      }
    ],
    [
      {
        "colspan": 1,
        "content": "BSA"
      },
      {
        "colspan": 1,
        "content": "Biotech, P06-139-1500"
      }
    ],
    [
      {
        "colspan": 1,
        "content": "DAPI"
      },
      {
        "colspan": 1,
        "content": "Sigma, D9542"
      }
    ],
    [
      {
        "colspan": 1,
        "content": "DAPI "
      },
      {
        "colspan": 1,
        "content": "Thermo Fischer Scientific, 00-4958-02"
      }
    ],
    [
      {
        "colspan": 1,
        "content": "Geltin"
      },
      {
        "colspan": 1,
        "content": "Difco 0143-01"
      }
    ]
  ]
}